setup.cfg
setup.py
yahoofantasyfootball/__init__.py
yahoofantasyfootball/soupselect.py
yahoofantasyfootball.egg-info/PKG-INFO
yahoofantasyfootball.egg-info/SOURCES.txt
yahoofantasyfootball.egg-info/dependency_links.txt
yahoofantasyfootball.egg-info/not-zip-safe
yahoofantasyfootball.egg-info/requires.txt
yahoofantasyfootball.egg-info/top_level.txt