Metadata-Version: 1.0
Name: yahoofantasyfootball
Version: 0.3
Summary: Web scraper for Yahoo! Fantasy Football data. Not affiliated with or endorsed by Yahoo!
Home-page: http://github.com/sbma44/yahoofantasyfootball
Author: Tom Lee
Author-email: thomas.j.lee@gmail.com
License: MIT
Platform: UNKNOWN
